{"desktop":{"rows":[{"ID":"","backgroundColorSticky":"","className":"","cols":[{"items":[{"style":{"backgroundColor":"","backgroundImage":"","backgroundPosition":"center center","backgroundRepeat":"no-repeat","backgroundSize":"cover","borderBottomWidth":0,"borderColor":"","borderLeftWidth":0,"borderRadius":0,"borderRightWidth":0,"borderStyle":"none","borderTopWidth":0,"marginBottom":"","marginLeft":"","marginRight":"","marginTop":"","paddingBottom":0,"paddingLeft":10,"paddingRight":10,"paddingTop":0},"ID":"","_rel":"text","alignVertical":"left","className":"","content":"<span style=\"color: #a3a3a3; font-size: 10px; letter-spacing: 0.4px;\">SALE NOW ON + FREE SHIPPING</span>","centerElement":false,"index":0,"selected":false},{"style":{},"_rel":"flex","index":1},{"style":{},"ID":"","_rel":"menu","alignVertical":"left","animation":"slide-in-on-top","background":{"backgroundColor":"#ffffff","backgroundImage":"","backgroundPosition":"center center","backgroundRepeat":"no-repeat","backgroundSize":"cover"},"backgroundColorMobile":"#f9f9f9","className":"","centerElement":false,"effect":"fade","hoverStyle":"default","iconColor":"#333333","iconColorMobile":"#333333","index":2,"itemSpacing":30,"layoutStyle":"text","link":{"borderRadius":0,"style":{"backgroundColorHover":"#ebebeb","color":"#a3a3a3","colorHover":"#ffffff","outlineColorHover":"#ebebeb","underlineColorHover":"#ebebeb"},"underlineStyle":"solid","underlineWidth":2},"menuID":"","menuStyle":"fullscreen","position":"left","selected":false,"spacing":{"backgroundColor":"","backgroundImage":"","backgroundPosition":"center center","backgroundRepeat":"no-repeat","backgroundSize":"cover","borderBottomWidth":0,"borderColor":"","borderLeftWidth":0,"borderRadius":0,"borderRightWidth":0,"borderStyle":"none","borderTopWidth":0,"marginBottom":"","marginLeft":"","marginRight":"","marginTop":"","paddingBottom":0,"paddingLeft":0,"paddingRight":0,"paddingTop":0},"subMenu":{"animation":"scale","animationVertical":"normal","background":"#292929","effectNormalVertical":"none","fontWeight":400,"link":{"style":{"color":"","colorHover":""}},"maginTop":"","style":{"fontSize":"","fontStyle":"normal","letterSpacing":"","lineHeight":"","textDecoration":"none","textTransform":"uppercase"},"width":220},"textAlign":"left","textSettings":{"fontFamily":"Poppins","fontSize":10,"fontStyle":"","fontWeight":"600","letterSpacing":0,"lineHeight":21,"textDecoration":"","textTransform":"uppercase"},"unitWidthSidebar":"px","verticalAlign":"middle","widthSidebar":300}],"style":{"backgroundColor":"","backgroundImage":"","backgroundPosition":"center center","backgroundRepeat":"no-repeat","backgroundSize":"cover","borderBottomWidth":0,"borderColor":"","borderLeftWidth":0,"borderRadius":0,"borderRightWidth":0,"borderStyle":"none","borderTopWidth":0,"marginBottom":"","marginTop":"","maxWidth":1170,"paddingBottom":"","paddingLeft":"","paddingRight":"","paddingTop":""},"unit":"px"}],"heightSticky":"","index":0,"selected":false,"sticky":false,"sticky_effect":"normal","style":{"backgroundColor":"#292929","backgroundImage":"","backgroundPosition":"center center","backgroundRepeat":"no-repeat","backgroundSize":"cover","borderBottomWidth":0,"borderColor":"","borderLeftWidth":0,"borderRadius":0,"borderRightWidth":0,"borderStyle":"none","borderTopWidth":0,"marginBottom":"","marginLeft":"","marginRight":"","marginTop":"","paddingBottom":"","paddingLeft":"","paddingRight":"","paddingTop":""},"textColorSticky":"","themeColor":false,"vertical":true},{"ID":"","backgroundColorSticky":"","className":"","cols":[{"items":[{"style":{"backgroundColor":"","backgroundImage":"","backgroundPosition":"center center","backgroundRepeat":"no-repeat","backgroundSize":"cover","borderBottomWidth":0,"borderColor":"","borderLeftWidth":0,"borderRadius":0,"borderRightWidth":0,"borderStyle":"none","borderTopWidth":0,"color":"#333333","fontFamily":"Lato","fontSize":20,"fontStyle":"","fontWeight":400,"letterSpacing":0,"lineHeight":30,"marginBottom":"","marginLeft":"","marginRight":"","marginTop":"","maxWidth":43,"paddingBottom":10,"paddingLeft":10,"paddingRight":10,"paddingTop":10,"textDecoration":""},"ID":"","_rel":"logo","alignVertical":"left","className":"","content":"Logo","centerElement":false,"index":0,"logoImage":"http://cdn.woorockets.com/files/header-templates/hoz-5/header-logo.png","logoImageRetina":"","logoImageSticky":"","logoImageStickyRetina":"","logoType":"image","selected":false,"maxWidthSticky":138},{"style":{},"ID":"","_rel":"menu","alignVertical":"left","animation":"slide-in-on-top","background":{"backgroundColor":"#ffffff","backgroundImage":"","backgroundPosition":"center center","backgroundRepeat":"no-repeat","backgroundSize":"cover"},"backgroundColorMobile":"#f9f9f9","className":"","centerElement":false,"effect":"fade","hoverStyle":"default","iconColor":"#333333","iconColorMobile":"#333333","index":1,"itemSpacing":50,"layoutStyle":"text","link":{"borderRadius":0,"style":{"backgroundColorHover":"#ebebeb","color":"#333333","colorHover":"#ff4064","outlineColorHover":"#ebebeb","underlineColorHover":"#ebebeb"},"underlineStyle":"solid","underlineWidth":2},"menuID":"","menuStyle":"fullscreen","position":"left","selected":false,"spacing":{"backgroundColor":"","backgroundImage":"","backgroundPosition":"center center","backgroundRepeat":"no-repeat","backgroundSize":"cover","borderBottomWidth":0,"borderColor":"","borderLeftWidth":0,"borderRadius":0,"borderRightWidth":0,"borderStyle":"none","borderTopWidth":0,"marginBottom":"","marginLeft":"","marginRight":"","marginTop":"","paddingBottom":10,"paddingLeft":10,"paddingRight":10,"paddingTop":10},"subMenu":{"animation":"scale","animationVertical":"normal","background":"","effectNormalVertical":"none","fontWeight":400,"link":{"style":{"color":"","colorHover":""}},"maginTop":"","style":{"fontSize":"","fontStyle":"normal","letterSpacing":"","lineHeight":"","textDecoration":"none","textTransform":"none"},"width":220},"textAlign":"left","textSettings":{"fontFamily":"Poppins","fontSize":12,"fontStyle":"","fontWeight":"600","letterSpacing":0,"lineHeight":21,"textDecoration":"","textTransform":"uppercase"},"unitWidthSidebar":"px","verticalAlign":"middle","widthSidebar":300},{"style":{},"_rel":"flex","index":2},{"style":{"backgroundColor":"","backgroundImage":"","backgroundPosition":"center center","backgroundRepeat":"no-repeat","backgroundSize":"cover","borderBottomWidth":0,"borderColor":"","borderLeftWidth":0,"borderRadius":0,"borderRightWidth":0,"borderStyle":"none","borderTopWidth":0,"marginBottom":"","marginLeft":"","marginRight":"","marginTop":"","paddingBottom":10,"paddingLeft":10,"paddingRight":10,"paddingTop":8},"ID":"","_rel":"shopping-cart","alignVertical":"left","animationDropdown":"dropdown-fade","animationSidebar":"sidebar-slide-in-on-top","className":"","centerElement":false,"colorType":"light","colorPrice":"#cc0000","titleText":"","colorTitle":"#333333","iconName":"nitro-icon-cart-8","index":3,"marginTop":"","position":"position-sidebar-left","selected":false,"showCartInfo":"item_number","styleIcon":{"color":"#000000","hoverColor":"#d6aa74","fontSize":20},"type":"dropdown"},{"style":{"backgroundColor":"","backgroundImage":"","backgroundPosition":"center center","backgroundRepeat":"no-repeat","backgroundSize":"cover","borderBottomWidth":0,"borderColor":"","borderLeftWidth":0,"borderRadius":0,"borderRightWidth":0,"borderStyle":"none","borderTopWidth":0,"marginBottom":"","marginLeft":"","marginRight":"","marginTop":"","paddingBottom":"","paddingLeft":10,"paddingRight":"","paddingTop":""},"ID":"","_rel":"search","alignVertical":"left","animation":"bottom-to-top","className":"","centerElement":false,"iconColor":"#000000","hoverIconColor":"#ff4064","iconFontSize":14,"index":4,"layout":"dropdown","liveSearch":{"active":false,"max_results":5,"min_characters":0,"searchIn":[],"show_category":false,"show_suggestion":false},"marginTop":"","searchStyle":"light-background","selected":false,"placeholder":"","widthInput":"300","buttonType":"icon","textButton":"Search","textColorButton":"#ffffff","bgColorButton":"#d6aa74","hoverTextColorButton":"#ffffff","hoverBgColorButton":"#dea35b"}],"style":{"backgroundColor":"","backgroundImage":"","backgroundPosition":"center center","backgroundRepeat":"no-repeat","backgroundSize":"cover","borderBottomWidth":0,"borderColor":"","borderLeftWidth":0,"borderRadius":0,"borderRightWidth":0,"borderStyle":"none","borderTopWidth":0,"marginBottom":"","marginTop":"","maxWidth":1170,"paddingBottom":"","paddingLeft":"","paddingRight":"","paddingTop":""},"unit":"px"}],"heightSticky":"","index":1,"selected":false,"sticky":false,"sticky_effect":"normal","style":{"backgroundColor":"","backgroundImage":"","backgroundPosition":"center center","backgroundRepeat":"no-repeat","backgroundSize":"cover","borderBottomWidth":0,"borderColor":"","borderLeftWidth":0,"borderRadius":0,"borderRightWidth":0,"borderStyle":"none","borderTopWidth":0,"marginBottom":"","marginLeft":"","marginRight":"","marginTop":"","paddingBottom":10,"paddingLeft":"","paddingRight":"","paddingTop":10},"textColorSticky":"","themeColor":false,"vertical":true}],"settings":{"ID":"","className":"","fixedList":{"miscellaneous":{"404":false,"home":false,"search":false,"blog":false},"custom_post_type_archives":{"product":false,"nitro-gallery":false},"taxonomies":{"category":false,"post_tag":false,"product_cat":false,"product_tag":false,"gallery_cat":false,"gallery_tag":false},"single":{"post":false,"wr_mapper":false,"product":false,"nitro-gallery":false},"pages":{"2":false,"4":false,"6":false,"7":false,"8":false,"10":false,"11":false,"12":false,"18":false,"20":false,"22":false,"127":false,"180":false,"182":false,"194":false,"196":false,"198":false,"200":false,"202":false,"204":false,"206":false,"208":false,"210":false,"212":false,"214":false,"216":false,"218":false,"220":false,"265":false,"266":false,"273":false,"279":false,"280":false,"281":false,"282":false,"283":false,"284":false,"285":false,"288":false,"309":false,"318":false,"319":false,"320":false,"321":false,"322":false,"323":false,"324":false,"339":false,"340":false,"341":false,"350":false,"351":false,"352":false,"353":false,"354":false,"355":false,"376":false,"377":false,"380":false,"381":false,"427":false,"428":false,"429":false,"430":false,"431":false,"432":false,"434":false,"448":false,"449":false,"450":false,"451":false,"452":false,"453":false,"454":false,"488":false,"489":false,"490":false,"491":false,"501":false,"503":false,"517":false,"672":false,"834":false,"1185":false,"1259":false,"1288":false,"1302":false,"1603":false,"1830":false,"1863":false,"1879":false,"1893":false,"2362":false,"2427":false,"2546":false,"2593":false,"2672":false,"2898":false,"2906":false,"2959":false,"2966":false,"2971":false,"3253":false,"3324":false,"3408":false,"3466":false,"3708":false,"3894":false,"3980":false,"4137":false,"4143":false,"4145":false,"4156":false,"4159":false,"4404":false,"4980":false,"5066":false}},"position":"inherit","positionVertical":"left","selected":false,"showHideFixed":"hide","style":{"backgroundColor":"","backgroundImage":"","backgroundPosition":"center center","backgroundRepeat":"no-repeat","backgroundSize":"cover","borderBottomWidth":0,"borderColor":"","borderLeftWidth":0,"borderRadius":0,"borderRightWidth":0,"borderStyle":"none","borderTopWidth":0,"marginBottom":"","marginLeft":"","marginRight":"","marginTop":"","paddingBottom":"","paddingLeft":"","paddingRight":"","paddingTop":"","width":400},"type":"horizontal","unit":"px"},"type":"desktop"},"mobile":{"rows":[{"ID":"","backgroundColorSticky":"","className":"","cols":[{"items":[{"style":{"backgroundColor":"","backgroundImage":"","backgroundPosition":"center center","backgroundRepeat":"no-repeat","backgroundSize":"cover","borderBottomWidth":0,"borderColor":"","borderLeftWidth":0,"borderRadius":0,"borderRightWidth":0,"borderStyle":"none","borderTopWidth":0,"color":"#333333","fontFamily":"Lato","fontSize":20,"fontStyle":"","fontWeight":400,"letterSpacing":0,"lineHeight":30,"marginBottom":"","marginLeft":"","marginRight":"","marginTop":"","maxWidth":40,"paddingBottom":15,"paddingLeft":10,"paddingRight":10,"paddingTop":15,"textDecoration":""},"ID":"","_rel":"logo","alignVertical":"left","className":"","content":"Logo","centerElement":false,"index":0,"logoImage":"http://cdn.woorockets.com/files/header-templates/hoz-5/logo-small.png","logoImageRetina":"http://cdn.woorockets.com/files/header-templates/hoz-5/logo-small.png","logoImageSticky":"","logoImageStickyRetina":"","logoType":"image","selected":false,"maxWidthSticky":138},{"style":{},"_rel":"flex","index":1},{"style":{"backgroundColor":"","backgroundImage":"","backgroundPosition":"center center","backgroundRepeat":"no-repeat","backgroundSize":"cover","borderBottomWidth":0,"borderColor":"","borderLeftWidth":0,"borderRadius":0,"borderRightWidth":0,"borderStyle":"none","borderTopWidth":0,"marginBottom":"","marginLeft":"","marginRight":"","marginTop":"","paddingBottom":10,"paddingLeft":10,"paddingRight":20,"paddingTop":10},"ID":"","_rel":"shopping-cart","alignVertical":"left","animationDropdown":"dropdown-fade","animationSidebar":"sidebar-slide-in-on-top","className":"","centerElement":false,"colorType":"light","colorPrice":"#cc0000","titleText":"","colorTitle":"#333333","iconName":"fa fa-shopping-cart","index":2,"marginTop":"","position":"position-sidebar-left","selected":false,"showCartInfo":"item_number","styleIcon":{"color":"#ffffff","hoverColor":"#d6aa74","fontSize":14},"type":"sidebar"},{"style":{},"ID":"","_rel":"menu","alignVertical":"left","animation":"slide-in-on-top","background":{"backgroundColor":"#ffffff","backgroundImage":"","backgroundPosition":"center center","backgroundRepeat":"no-repeat","backgroundSize":"cover"},"backgroundColorMobile":"#f9f9f9","className":"","centerElement":false,"effect":"fade","hoverStyle":"default","iconColor":"#333333","iconColorMobile":"#ffffff","index":3,"itemSpacing":30,"layoutStyle":"text","link":{"borderRadius":0,"style":{"backgroundColorHover":"#ebebeb","color":"#333333","colorHover":"#d6aa74","outlineColorHover":"#ebebeb","underlineColorHover":"#ebebeb"},"underlineStyle":"solid","underlineWidth":2},"menuID":"","menuStyle":"fullscreen","position":"left","selected":false,"spacing":{"backgroundColor":"","backgroundImage":"","backgroundPosition":"center center","backgroundRepeat":"no-repeat","backgroundSize":"cover","borderBottomWidth":0,"borderColor":"","borderLeftWidth":0,"borderRadius":0,"borderRightWidth":0,"borderStyle":"none","borderTopWidth":0,"marginBottom":"","marginLeft":"","marginRight":"","marginTop":"","paddingBottom":10,"paddingLeft":10,"paddingRight":10,"paddingTop":10},"subMenu":{"animation":"scale","animationVertical":"normal","background":"","effectNormalVertical":"none","fontWeight":400,"link":{"style":{"color":"","colorHover":""}},"maginTop":"","style":{"fontSize":"","fontStyle":"normal","letterSpacing":"","lineHeight":"","textDecoration":"none","textTransform":"none"},"width":220},"textAlign":"left","textSettings":{"fontFamily":"Lato","fontSize":13,"fontStyle":"","fontWeight":400,"letterSpacing":0,"lineHeight":21,"textDecoration":"","textTransform":"none"},"unitWidthSidebar":"px","verticalAlign":"middle","widthSidebar":300}],"style":{"backgroundColor":"","backgroundImage":"","backgroundPosition":"center center","backgroundRepeat":"no-repeat","backgroundSize":"cover","borderBottomWidth":0,"borderColor":"","borderLeftWidth":0,"borderRadius":0,"borderRightWidth":0,"borderStyle":"none","borderTopWidth":0,"marginBottom":"","marginTop":"","maxWidth":94,"paddingBottom":"","paddingLeft":"","paddingRight":"","paddingTop":""},"unit":"%"}],"heightSticky":"","index":0,"selected":false,"sticky":false,"sticky_effect":"normal","style":{"backgroundColor":"#252525","backgroundImage":"","backgroundPosition":"center center","backgroundRepeat":"no-repeat","backgroundSize":"cover","borderBottomWidth":0,"borderColor":"","borderLeftWidth":0,"borderRadius":0,"borderRightWidth":0,"borderStyle":"none","borderTopWidth":0,"marginBottom":"","marginLeft":"","marginRight":"","marginTop":"","paddingBottom":"","paddingLeft":"","paddingRight":"","paddingTop":""},"textColorSticky":"","themeColor":false,"vertical":true}],"settings":{"ID":"","className":"","fixedList":{"miscellaneous":{"404":false,"home":false,"search":false,"blog":false},"custom_post_type_archives":{"product":false,"nitro-gallery":false},"taxonomies":{"category":false,"post_tag":false,"product_cat":false,"product_tag":false,"gallery_cat":false,"gallery_tag":false},"single":{"post":false,"wr_mapper":false,"product":false,"nitro-gallery":false},"pages":{"2":false,"4":false,"6":false,"7":false,"8":false,"10":false,"11":false,"12":false,"18":false,"20":false,"22":false,"127":false,"180":false,"182":false,"194":false,"196":false,"198":false,"200":false,"202":false,"204":false,"206":false,"208":false,"210":false,"212":false,"214":false,"216":false,"218":false,"220":false,"265":false,"266":false,"273":false,"279":false,"280":false,"281":false,"282":false,"283":false,"284":false,"285":false,"288":false,"309":false,"318":false,"319":false,"320":false,"321":false,"322":false,"323":false,"324":false,"339":false,"340":false,"341":false,"350":false,"351":false,"352":false,"353":false,"354":false,"355":false,"376":false,"377":false,"380":false,"381":false,"427":false,"428":false,"429":false,"430":false,"431":false,"432":false,"434":false,"448":false,"449":false,"450":false,"451":false,"452":false,"453":false,"454":false,"488":false,"489":false,"490":false,"491":false,"501":false,"503":false,"517":false,"672":false,"834":false,"1185":false,"1259":false,"1288":false,"1302":false,"1603":false,"1830":false,"1863":false,"1879":false,"1893":false,"2362":false,"2427":false,"2546":false,"2593":false,"2672":false,"2898":false,"2906":false,"2959":false,"2966":false,"2971":false,"3253":false,"3324":false,"3408":false,"3466":false,"3708":false,"3894":false,"3980":false,"4137":false,"4143":false,"4145":false,"4156":false,"4159":false,"4404":false,"4980":false,"5066":false}},"position":"inherit","positionVertical":"left","selected":"","showHideFixed":"hide","style":{"backgroundColor":"","backgroundImage":"","backgroundPosition":"center center","backgroundRepeat":"no-repeat","backgroundSize":"cover","borderBottomWidth":0,"borderColor":"","borderLeftWidth":0,"borderRadius":0,"borderRightWidth":0,"borderStyle":"none","borderTopWidth":0,"marginBottom":"","marginLeft":"","marginRight":"","marginTop":"","paddingBottom":"","paddingLeft":"","paddingRight":"","paddingTop":"","width":400},"type":"horizontal","unit":"px"},"type":"mobile"},"layout":"desktop","hbLayout":"horizontal","switchLayout":true,"creatFirst":true}